[
  {
    "content_id": 336792,
    "reference_id": 26500,
    "version": "1.0.0",
    "title": "Hebreos",
    "media_type": "Text",
    "index_reference": "58000000",
    "language": "spa",
    "content": "<p>La Carta a los Hebreos</p><h2>Propósito</h2><p>Fomentar la perseverancia en el sufrimiento, principalmente destacando la superioridad de Cristo y la suficiencia de su obra</p><h2>Autor</h2><p>Desconocido</p><h2>Fecha</h2><p>Lo más probable es a principios de los años 60 d.C., pero una fecha posterior al 70 d.C. también es posible</p><h2>Contexto</h2><p>Escrito a un grupo de cristianos (probablemente en Roma) que estaban siendo perseguidos y luchando por mantener su fe</p>",
    "associations": {
      "passage": [
        {
          "start_ref": "58001001",
          "start_ref_usfm": "HEB 1:1",
          "end_ref": "58001001",
          "end_ref_usfm": "HEB 1:1"
        }
      ],
      "resource": []
    }
  }
]