[
  {
    "content_id": 27629,
    "reference_id": 26480,
    "version": "1.0.0",
    "title": "Zakharia",
    "media_type": "Text",
    "index_reference": "38000000",
    "language": "ind",
    "content": "<p>Kitab Zakharia</p><h2>Tujuan</h2><p>Menumbuhkan pembaruan rohani dan mengumumkan masa depan yang agung bagi umat Allah</p><h2>Penulis</h2><p>Zakharia</p><h2>Tahun penulisan</h2><p>Kemungkinan antara tahun 520 dan 470 SM</p><h2>Latar Belakang</h2><p>Yerusalem, beberapa puluh tahun setelah sekelompok sisa bangsa Yahudi kembali dari pembuangan</p>",
    "associations": {
      "passage": [
        {
          "start_ref": "38001001",
          "start_ref_usfm": "ZEC 1:1",
          "end_ref": "38001001",
          "end_ref_usfm": "ZEC 1:1"
        }
      ],
      "resource": []
    }
  }
]